{
  "ID": "LAYOUT_COLUMNS_HIERARCHIES_DF",
  "Name": "Organize columns and hierarchies in display folders",
  "Category": "Model Layout",
  "Description": "Tables with more than 10 visible columns and/or hierarchies should have them organized in display folders for improved usability.",
  "Severity": 1,
  "Scope": "Table",
  "Expression": "Columns.Count(IsVisible and string.IsNullOrEmpty(DisplayFolder)) +\nHierarchies.Count(IsVisible and string.IsNullOrEmpty(DisplayFolder))\n> 10",
  "CompatibilityLevel": 1200
}
